MANIFEST.in
README.txt
bagtest.py
ez_setup.py
setup.cfg
setup.py
pybagit/__init__.py
pybagit/bagit.py
pybagit/bench.py
pybagit/exceptions.py
pybagit/multichecksum.py
pybagit.egg-info/PKG-INFO
pybagit.egg-info/SOURCES.txt
pybagit.egg-info/dependency_links.txt
pybagit.egg-info/top_level.txt
test/.DS_Store
test/__init__.py
test/__init__.pyc
test/bagcompress.py
test/bagcompress.pyc
test/bagcreate.py
test/bagcreate.pyc
test/bagfetch.py
test/bagfetch.pyc
test/bagmanifest.py
test/bagmanifest.pyc
test/bagupdate.py
test/bagupdate.pyc
test/bagversion.py
test/bagversion.pyc
test/manifest-sha1.txt
test/testbag/bag-info.txt
test/testbag/bagit.txt
test/testbag/fetch.txt
test/testbag/manifest-sha1.txt
test/testbag/tagmanifest-sha1.txt
test/testbag/data/.keep
test/testbag/data/Kopiâren.htm
test/testbag/data/tëst.gif
test/testbag/data/subdir/subsubdir/angry.jpg
test/tëst/bag-info.txt
test/tëst/bagit.txt
test/tëst/fetch.txt
test/tëst/manifest-sha1.txt
test/tëst/tagmanifest-sha1.txt