Metadata-Version: 1.1
Name: pybagit
Version: 1.5.2
Summary: A library for dealing with BagIt packages.
Home-page: http://ahankinson.github.io/pybagit
Author: Andrew Hankinson
Author-email: andrew.hankinson@mail.mcgill.ca
License: http://www.opensource.org/licenses/mit-license.php
Platform: UNKNOWN
Classifier: Development Status :: 5 - Production/Stable
Classifier: Intended Audience :: Information Technology
Classifier: License :: OSI Approved :: MIT License
Classifier: Operating System :: OS Independent
Classifier: Topic :: Internet
Classifier: Topic :: Software Development :: Libraries
Classifier: Topic :: System :: Archiving :: Packaging
